chatcli_gpt/__init__.py
chatcli_gpt/__main__.py
chatcli_gpt/cli.py
chatcli_gpt/conversation.py
chatcli_gpt/data/default_log
chatcli_gpt/log.py
chatcli_gpt/models.py
chatcli_gpt/plugins.py
chatcli_gpt-0.9.0.dist-info/LICENSE
chatcli_gpt-0.9.0.dist-info/METADATA
chatcli_gpt-0.9.0.dist-info/WHEEL
chatcli_gpt-0.9.0.dist-info/entry_points.txt
chatcli_gpt-0.9.0.dist-info/RECORD
