Metadata-Version: 2.1
Name: chatcli-gpt
Version: 0.9.0
Summary: A command line interface for interacting with GPT-3. It's orientated around an append only chat log so you get a complete history of your conversations.
Home-page: https://github.com/cthulahoops/chatcli
License: MIT
Author: Adam Kelly
Author-email: adam@cthulahoops.org
Requires-Python: >=3.10,<4.0
Classifier: License :: OSI Approved :: MIT License
Classifier: Programming Language :: Python :: 3
Classifier: Programming Language :: Python :: 3.10
Classifier: Programming Language :: Python :: 3.11
Requires-Dist: click (>=8.1.3,<9.0.0)
Requires-Dist: click-default-group (>=1.2.2,<2.0.0)
Requires-Dist: duckduckgo-search (>=2.8.5,<3.0.0)
Requires-Dist: markdown (>=3.4.1,<4.0.0)
Requires-Dist: openai (>=1.42.0,<2.0.0)
Requires-Dist: prompt-toolkit (>=3.0.38,<4.0.0)
Requires-Dist: python-dateutil (>=2.8.2,<3.0.0)
Requires-Dist: rich (>=13.7.0,<14.0.0)
Requires-Dist: tiktoken (>=0.5.1,<0.6.0)
Requires-Dist: wolframalpha (>=5.0.0,<6.0.0)
Project-URL: Repository, https://github.com/cthulahoops/chatcli
